video_annotator/__init__.py
video_annotator/annotator.py
video_annotator/cropper.py
video_annotator/tracker.py
video_annotator-0.1.1.dist-info/LICENSE
video_annotator-0.1.1.dist-info/METADATA
video_annotator-0.1.1.dist-info/WHEEL
video_annotator-0.1.1.dist-info/top_level.txt
video_annotator-0.1.1.dist-info/RECORD
