Metadata-Version: 2.1
Name: video-annotator
Version: 0.1.1
Summary: A Python package for video annotation, object tracking, and cropping
Home-page: https://github.com/jelimutaalidev/video-annotator
Author: Moh. Jeli Almuta'ali
Author-email: jelimutaalidev@gmail.com
Classifier: Programming Language :: Python :: 3
Classifier: License :: OSI Approved :: MIT License
Classifier: Operating System :: OS Independent
Requires-Python: >=3.6
License-File: LICENSE
Requires-Dist: supervision >=0.1.1
Requires-Dist: tqdm >=4.50.0
